rtl/clock_divider.v
module clock_divider(

    input clk,
    input reset,
    output reg slow_clk

);

//====================================================
// 100 MHz CLOCK DIVIDER
//====================================================

// 100,000,000 clock cycles = 1 second

reg [26:0] counter;

always @(posedge clk or posedge reset)
begin

    if(reset)
    begin
        counter <= 0;
        slow_clk <= 0;
    end

    else
    begin

        if(counter == 2)
        begin
            slow_clk <= ~slow_clk;
            counter <= 0;
        end

        else
            counter <= counter + 1;

    end

end

endmodule

rtl/traffic_light_controller.v
module traffic_light_controller(

    input clk,
    input reset,

    output reg A_R,
    output reg A_Y,
    output reg A_G,

    output reg B_R,
    output reg B_Y,
    output reg B_G

);

//====================================================
// INTERNAL SLOW CLOCK
//====================================================

wire slow_clk;


//====================================================
// CLOCK DIVIDER INSTANTIATION
//====================================================

clock_divider clk_div(

    .clk(clk),
    .reset(reset),
    .slow_clk(slow_clk)

);


//====================================================
// STATE DECLARATION
//====================================================

parameter S0 = 2'b00;
parameter S1 = 2'b01;
parameter S2 = 2'b10;
parameter S3 = 2'b11;

reg [1:0] current_state, next_state;


//====================================================
// COUNTER
//====================================================

reg [3:0] counter;


//====================================================
// STATE REGISTER + COUNTER
//====================================================

always @(posedge slow_clk or posedge reset)
begin

    if(reset)
    begin
        current_state <= S0;
        counter <= 0;
    end

    else
    begin

        current_state <= next_state;

        if(current_state != next_state)
            counter <= 0;

        else
            counter <= counter + 1;

    end

end


//====================================================
// NEXT STATE LOGIC
//====================================================

always @(*)
begin

    case(current_state)

        S0:
        begin
            if(counter >= 2)
                next_state = S1;
            else
                next_state = S0;
        end

        S1:
        begin
            if(counter >= 1)
                next_state = S2;
            else
                next_state = S1;
        end

        S2:
        begin
            if(counter >= 2)
                next_state = S3;
            else
                next_state = S2;
        end

        S3:
        begin
            if(counter >= 1)
                next_state = S0;
            else
                next_state = S3;
        end

        default:
            next_state = S0;

    endcase

end


//====================================================
// OUTPUT LOGIC
//====================================================

always @(*)
begin

    // Default Outputs

    A_R = 0;
    A_Y = 0;
    A_G = 0;

    B_R = 0;
    B_Y = 0;
    B_G = 0;

    case(current_state)

        //--------------------------------------------
        // ROAD A GREEN
        //--------------------------------------------
        S0:
        begin
            A_G = 1;
            B_R = 1;
        end

        //--------------------------------------------
        // ROAD A YELLOW
        //--------------------------------------------
        S1:
        begin
            A_Y = 1;
            B_R = 1;
        end

        //--------------------------------------------
        // ROAD B GREEN
        //--------------------------------------------
        S2:
        begin
            A_R = 1;
            B_G = 1;
        end

        //--------------------------------------------
        // ROAD B YELLOW
        //--------------------------------------------
        S3:
        begin
            A_R = 1;
            B_Y = 1;
        end

    endcase

end

endmodule

tb/traffic_light_tb.v
`timescale 1ns / 1ps

module traffic_light_tb;

//====================================================
// INPUTS
//====================================================

reg clk;
reg reset;


//====================================================
// OUTPUTS
//====================================================

wire A_R;
wire A_Y;
wire A_G;

wire B_R;
wire B_Y;
wire B_G;


//====================================================
// DUT INSTANTIATION
//====================================================

traffic_light_controller DUT(

    .clk(clk),
    .reset(reset),

    .A_R(A_R),
    .A_Y(A_Y),
    .A_G(A_G),

    .B_R(B_R),
    .B_Y(B_Y),
    .B_G(B_G)

);


//====================================================
// CLOCK GENERATION
//====================================================

always #5 clk = ~clk;


//====================================================
// TEST SEQUENCE
//====================================================

initial
begin

    $dumpfile("traffic.vcd");
    $dumpvars(0, traffic_light_tb);
    
    clk = 0;
    reset = 1;

    #20;
    reset = 0;

    #5000;
    
    $finish;
    
    $monitor("TIME=%0t | A_G=%b A_Y=%b A_R=%b | B_G=%b B_Y=%b B_R=%b",
    $time, A_G, A_Y, A_R, B_G, B_Y, B_R);
    
end

endmodule

visualization/traffic.vcd
$date
   Fri May 29 23:28:03 2026
$end

$version
  2025.1.0
  $dumpfile ("traffic.vcd") 
$end

$timescale
  1ps
$end

$scope module traffic_light_tb $end
$var reg 1 ! clk $end
$var reg 1 " reset $end
$var wire 1 # A_R $end
$var wire 1 $ A_Y $end
$var wire 1 % A_G $end
$var wire 1 & B_R $end
$var wire 1 ' B_Y $end
$var wire 1 ( B_G $end
$scope module DUT $end
$var wire 1 ) clk $end
$var wire 1 * reset $end
$var reg 1 + A_R $end
$var reg 1 , A_Y $end
$var reg 1 - A_G $end
$var reg 1 . B_R $end
$var reg 1 / B_Y $end
$var reg 1 0 B_G $end
$var wire 1 1 slow_clk $end
$var reg 2 2 current_state [1:0] $end
$var reg 2 3 next_state [1:0] $end
$var reg 4 4 counter [3:0] $end
$scope module clk_div $end
$var wire 1 ) clk $end
$var wire 1 * reset $end
$var reg 1 5 slow_clk $end
$var reg 27 6 counter [26:0] $end
$upscope $end
$upscope $end
$upscope $end
$enddefinitions $end

#0
$dumpvars
0!
1"
0#
0$
1%
1&
0'
0(
0)
1*
0+
0,
1-
1.
0/
00
01
b0 2
b0 3
b0 4
05
b0 6
$end

#5000
1!
1)

#10000
0!
0)

#15000
1!
1)

#20000
0!
0"
0)
0*

#25000
1!
1)
b1 6

#30000
0!
0)

#35000
1!
1)
b10 6

#40000
0!
0)

#45000
1!
1)
11
b1 4
15
b0 6

#50000
0!
0)

#55000
1!
1)
b1 6

#60000
0!
0)

#65000
1!
1)
b10 6

#70000
0!
0)

#75000
1!
1)
01
05
b0 6

#80000
0!
0)

#85000
1!
1)
b1 6

#90000
0!
0)

#95000
1!
1)
b10 6

#100000
0!
0)

#105000
1!
1)
11
b1 3
b10 4
15
b0 6

#110000
0!
0)

#115000
1!
1)
b1 6

#120000
0!
0)

#125000
1!
1)
b10 6

#130000
0!
0)

#135000
1!
1)
01
05
b0 6

#140000
0!
0)

#145000
1!
1)
b1 6

#150000
0!
0)

#155000
1!
1)
b10 6

#160000
0!
0)

#165000
1!
1$
0%
1)
1,
0-
1.
11
b1 2
b0 4
15
b0 6

#170000
0!
0)

#175000
1!
1)
b1 6

#180000
0!
0)

#185000
1!
1)
b10 6

#190000
0!
0)

#195000
1!
1)
01
05
b0 6

#200000
0!
0)

#205000
1!
1)
b1 6

#210000
0!
0)

#215000
1!
1)
b10 6

#220000
0!
0)

#225000
1!
1)
11
b10 3
b1 4
15
b0 6

#230000
0!
0)

#235000
1!
1)
b1 6

#240000
0!
0)

#245000
1!
1)
b10 6

#250000
0!
0)

#255000
1!
1)
01
05
b0 6

#260000
0!
0)

#265000
1!
1)
b1 6

#270000
0!
0)

#275000
1!
1)
b10 6

#280000
0!
0)

#285000
1!
1#
0$
0&
1(
1)
1+
0,
0.
10
11
b10 2
b0 4
15
b0 6

#290000
0!
0)

#295000
1!
1)
b1 6

#300000
0!
0)

#305000
1!
1)
b10 6

#310000
0!
0)

#315000
1!
1)
01
05
b0 6

#320000
0!
0)

#325000
1!
1)
b1 6

#330000
0!
0)

#335000
1!
1)
b10 6

#340000
0!
0)

#345000
1!
1)
11
b1 4
15
b0 6

#350000
0!
0)

#355000
1!
1)
b1 6

#360000
0!
0)

#365000
1!
1)
b10 6

#370000
0!
0)

#375000
1!
1)
01
05
b0 6

#380000
0!
0)

#385000
1!
1)
b1 6

#390000
0!
0)

#395000
1!
1)
b10 6

#400000
0!
0)

#405000
1!
1)
11
b11 3
b10 4
15
b0 6

#410000
0!
0)

#415000
1!
1)
b1 6

#420000
0!
0)

#425000
1!
1)
b10 6

#430000
0!
0)

#435000
1!
1)
01
05
b0 6

#440000
0!
0)

#445000
1!
1)
b1 6

#450000
0!
0)

#455000
1!
1)
b10 6

#460000
0!
0)

#465000
1!
1'
0(
1)
1+
1/
00
11
b11 2
b0 4
15
b0 6

#470000
0!
0)

#475000
1!
1)
b1 6

#480000
0!
0)

#485000
1!
1)
b10 6

#490000
0!
0)

#495000
1!
1)
01
05
b0 6

#500000
0!
0)

#505000
1!
1)
b1 6

#510000
0!
0)

#515000
1!
1)
b10 6

#520000
0!
0)

#525000
1!
1)
11
b0 3
b1 4
15
b0 6

#530000
0!
0)

#535000
1!
1)
b1 6

#540000
0!
0)

#545000
1!
1)
b10 6

#550000
0!
0)

#555000
1!
1)
01
05
b0 6

#560000
0!
0)

#565000
1!
1)
b1 6

#570000
0!
0)

#575000
1!
1)
b10 6

#580000
0!
0)

#585000
1!
0#
1%
1&
0'
1)
0+
1-
1.
0/
11
b0 2
b0 4
15
b0 6

#590000
0!
0)

#595000
1!
1)
b1 6

#600000
0!
0)

#605000
1!
1)
b10 6

#610000
0!
0)

#615000
1!
1)
01
05
b0 6

#620000
0!
0)

#625000
1!
1)
b1 6

#630000
0!
0)

#635000
1!
1)
b10 6

#640000
0!
0)

#645000
1!
1)
11
b1 4
15
b0 6

#650000
0!
0)

#655000
1!
1)
b1 6

#660000
0!
0)

#665000
1!
1)
b10 6

#670000
0!
0)

#675000
1!
1)
01
05
b0 6

#680000
0!
0)

#685000
1!
1)
b1 6

#690000
0!
0)

#695000
1!
1)
b10 6

#700000
0!
0)

#705000
1!
1)
11
b1 3
b10 4
15
b0 6

#710000
0!
0)

#715000
1!
1)
b1 6

#720000
0!
0)

#725000
1!
1)
b10 6

#730000
0!
0)

#735000
1!
1)
01
05
b0 6

#740000
0!
0)

#745000
1!
1)
b1 6

#750000
0!
0)

#755000
1!
1)
b10 6

#760000
0!
0)

#765000
1!
1$
0%
1)
1,
0-
1.
11
b1 2
b0 4
15
b0 6

#770000
0!
0)

#775000
1!
1)
b1 6

#780000
0!
0)

#785000
1!
1)
b10 6

#790000
0!
0)

#795000
1!
1)
01
05
b0 6

#800000
0!
0)

#805000
1!
1)
b1 6

#810000
0!
0)

#815000
1!
1)
b10 6

#820000
0!
0)

#825000
1!
1)
11
b10 3
b1 4
15
b0 6

#830000
0!
0)

#835000
1!
1)
b1 6

#840000
0!
0)

#845000
1!
1)
b10 6

#850000
0!
0)

#855000
1!
1)
01
05
b0 6

#860000
0!
0)

#865000
1!
1)
b1 6

#870000
0!
0)

#875000
1!
1)
b10 6

#880000
0!
0)

#885000
1!
1#
0$
0&
1(
1)
1+
0,
0.
10
11
b10 2
b0 4
15
b0 6

#890000
0!
0)

#895000
1!
1)
b1 6

#900000
0!
0)

#905000
1!
1)
b10 6

#910000
0!
0)

#915000
1!
1)
01
05
b0 6

#920000
0!
0)

#925000
1!
1)
b1 6

#930000
0!
0)

#935000
1!
1)
b10 6

#940000
0!
0)

#945000
1!
1)
11
b1 4
15
b0 6

#950000
0!
0)

#955000
1!
1)
b1 6

#960000
0!
0)

#965000
1!
1)
b10 6

#970000
0!
0)

#975000
1!
1)
01
05
b0 6

#980000
0!
0)

#985000
1!
1)
b1 6

#990000
0!
0)

#995000
1!
1)
b10 6
